Workbook
Name Slicer_Region: #N/A
Name Slicer_Years__Invoice_Date: #N/A

Sheet Data
B2: Retailer Dataset
B4: Retailer | C4: Retailer ID | D4: Invoice Date | E4: Region | F4: State | G4: City | H4: Beverage Brand | I4: Price per Unit | J4: Units Sold | K4: Total Sales | L4: Operating Profit | M4: Operating Margin
B5: BevCo | C5: 1185732 | D5: 44562 | E5: Northeast | F5: New York | G5: New York | H5: Coca-Cola | I5: 0.5 | J5: 12000 | K5: 6000 | L5: 3000 | M5: 0.5
B6: BevCo | C6: 1185732 | D6: 44563 | E6: Northeast | F6: New York | G6: New York | H6: Diet Coke | I6: 0.5 | J6: 10000 | K6: 5000 | L6: 1500 | M6: 0.3
B7: BevCo | C7: 1185732 | D7: 44564 | E7: Northeast | F7: New York | G7: New York | H7: Sprite | I7: 0.4 | J7: 10000 | K7: 4000 | L7: 1400 | M7: 0.35
B8: BevCo | C8: 1185732 | D8: 44565 | E8: Northeast | F8: New York | G8: New York | H8: Fanta | I8: 0.45 | J8: 8500 | K8: 3825 | L8: 1338.75 | M8: 0.35
B9: BevCo | C9: 1185732 | D9: 44566 | E9: Northeast | F9: New York | G9: New York | H9: Powerade | I9: 0.6 | J9: 9000 | K9: 5400 | L9: 1620 | M9: 0.3
B10: BevCo | C10: 1185732 | D10: 44567 | E10: Northeast | F10: New York | G10: New York | H10: Dasani Water | I10: 0.5 | J10: 10000 | K10: 5000 | L10: 1250 | M10: 0.25
B11: BevCo | C11: 1185732 | D11: 44568 | E11: Northeast | F11: New York | G11: New York | H11: Coca-Cola | I11: 0.5 | J11: 12500 | K11: 6250 | L11: 3125 | M11: 0.5
B12: BevCo | C12: 1185732 | D12: 44569 | E12: Northeast | F12: New York | G12: New York | H12: Diet Coke | I12: 0.5 | J12: 9000 | K12: 4500 | L12: 1350 | M12: 0.3
B13: BevCo | C13: 1185732 | D13: 44582 | E13: Northeast | F13: New York | G13: New York | H13: Sprite | I13: 0.4 | J13: 9500 | K13: 3800 | L13: 1330 | M13: 0.35
B14: BevCo | C14: 1185732 | D14: 44583 | E14: Northeast | F14: New York | G14: New York | H14: Fanta | I14: 0.45 | J14: 8250 | K14: 3712.5 | L14: 1299.375 | M14: 0.35
B15: BevCo | C15: 1185732 | D15: 44584 | E15: Northeast | F15: New York | G15: New York | H15: Powerade | I15: 0.6 | J15: 9000 | K15: 5400 | L15: 1620 | M15: 0.3
B16: BevCo | C16: 1185732 | D16: 44585 | E16: Northeast | F16: New York | G16: New York | H16: Dasani Water | I16: 0.5 | J16: 10000 | K16: 5000 | L16: 1250 | M16: 0.25
... B9652: BevCo | C9652: 1185732 | D9652: 44979 | E9652: Northeast | F9652: New Hampshire | G9652: Manchester | H9652: Sprite | I9652: 0.29 | J9652: 830 | K9652: 240.7 | L9652: 64.989 | M9652: 0.27

Sheet Analyze
A3: Sum of Total Sales | B3: Sum of Units Sold | C3: Average of Price per Unit | D3: Sum of Operating Profit
A4: 12016665 | B4: 24788610 | C4: 0.45216625 | D4: 4722496.8
A7: Sum of Total Sales | B7: Years (Invoice Date)
A8: Beverage Brand | B8: 2022 | C8: 2023 | D8: Grand Total
A9: Coca-Cola | B9: 499102 | C9: 2268974.9 | D9: 2768076.9
A10: Dasani Water | B10: 469270.7 | C10: 1917827.8 | D10: 2387098.5
A11: Diet Coke | B11: 423758.7 | C11: 1633959.3 | D11: 2057718
A12: Fanta | B12: 315489.2 | C12: 1116062.9 | D12: 1431552.1
A13: Powerade | B13: 349533.9 | C13: 1302529.3 | D13: 1652063.2
A14: Sprite | B14: 366578 | C14: 1353578.3 | D14: 1720156.3
A15: Grand Total | B15: 2423732.5 | C15: 9592932.5 | D15: 12016665
A18: Sum of Total Sales | B18: Years (Invoice Date)
A19: Retailer | B19: 2022 | C19: 2023 | D19: Grand Total
A20: Amazon | B20: 276210 | C20: 1009698.7 | D20: 1285908.7
A21: BevCo | B21: 466788 | C21: 2327606.5 | D21: 2794394.5
A22: FizzyCo | B22: 161210.1 | C22: 2262827.1 | D22: 2424037.2
A23: Target | B23: 9250.3 | C23: 1341995 | D23: 1351245.3
A24: Walmart | B24: 339912.5 | C24: 580211 | D24: 920123.5
A25: West Soda | B25: 1170361.6 | C25: 2070594.2 | D25: 3240955.8
A26: Grand Total | B26: 2423732.5 | C26: 9592932.5 | D26: 12016665
A29: Years (Invoice Date) | B29: Quarters (Invoice Date) | C29: Sum of Total Sales | D29: Average of Operating Margin
A30: 2022 | B30: Qtr1 | C30: 692776.1 | D30: 0.40174684 | E30: =A30 -> 2022 | F30: =B30 -> Qtr1 | G30: =C30 -> 692776.1 | H30: =D30 -> 0.40174684
B31: Qtr2 | C31: 644203.9 | D31: 0.4 | E31: =A31 -> 0 | F31: =B31 -> Qtr2 | G31: =C31 -> 644203.9 | H31: =D31 -> 0.4
B32: Qtr3 | C32: 719170.4 | D32: 0.41026549 | E32: =A32 -> 0 | F32: =B32 -> Qtr3 | G32: =C32 -> 719170.4 | H32: =D32 -> 0.41026549
B33: Qtr4 | C33: 367582.1 | D33: 0.40243816 | E33: =A33 -> 0 | F33: =B33 -> Qtr4 | G33: =C33 -> 367582.1 | H33: =D33 -> 0.40243816
A34: 2023 | B34: Qtr1 | C34: 1877584.3 | D34: 0.41657045 | E34: =A34 -> 2023 | F34: =B34 -> Qtr1 | G34: =C34 -> 1877584.3 | H34: =D34 -> 0.41657045
B35: Qtr2 | C35: 2379424.8 | D35: 0.42755819 | E35: =A35 -> 0 | F35: =B35 -> Qtr2 | G35: =C35 -> 2379424.8 | H35: =D35 -> 0.42755819
B36: Qtr3 | C36: 2805752.5 | D36: 0.4347017 | E36: =A36 -> 0 | F36: =B36 -> Qtr3 | G36: =C36 -> 2805752.5 | H36: =D36 -> 0.4347017
B37: Qtr4 | C37: 2530170.9 | D37: 0.42483933 | E37: =A37 -> 0 | F37: =B37 -> Qtr4 | G37: =C37 -> 2530170.9 | H37: =D37 -> 0.42483933
A38: Grand Total | C38: 12016665 | D38: 0.42299129

Sheet Dashboard
C11: Sales by Beverage Brand | H11: Sales by Retailer
C12: Brand | D12: Sales 2022 | E12: Sales 2023 | F12: Variance | H12: Retailer | I12: Sales 2022 | J12: Sales 2023 | K12: Variance
C13: =Analyze!A9 -> Coca-Cola | D13: =Analyze!B9 -> 499102 | E13: =Analyze!C9 -> 2268974.9 | F13: =E13-D13 -> 1769872.9 | H13: =Analyze!A20 -> Amazon | I13: =Analyze!B20 -> 276210 | J13: =Analyze!C20 -> 1009698.7 | K13: =J13-I13 -> 733488.7
C14: =Analyze!A10 -> Dasani Water | D14: =Analyze!B10 -> 469270.7 | E14: =Analyze!C10 -> 1917827.8 | F14: =E14-D14 -> 1448557.1 | H14: =Analyze!A21 -> BevCo | I14: =Analyze!B21 -> 466788 | J14: =Analyze!C21 -> 2327606.5 | K14: =J14-I14 -> 1860818.5
C15: =Analyze!A11 -> Diet Coke | D15: =Analyze!B11 -> 423758.7 | E15: =Analyze!C11 -> 1633959.3 | F15: =E15-D15 -> 1210200.6 | H15: =Analyze!A22 -> FizzyCo | I15: =Analyze!B22 -> 161210.1 | J15: =Analyze!C22 -> 2262827.1 | K15: =J15-I15 -> 2101617
C16: =Analyze!A12 -> Fanta | D16: =Analyze!B12 -> 315489.2 | E16: =Analyze!C12 -> 1116062.9 | F16: =E16-D16 -> 800573.7 | H16: =Analyze!A23 -> Target | I16: =Analyze!B23 -> 9250.3 | J16: =Analyze!C23 -> 1341995 | K16: =J16-I16 -> 1332744.7
C17: =Analyze!A13 -> Powerade | D17: =Analyze!B13 -> 349533.9 | E17: =Analyze!C13 -> 1302529.3 | F17: =E17-D17 -> 952995.4 | H17: =Analyze!A24 -> Walmart | I17: =Analyze!B24 -> 339912.5 | J17: =Analyze!C24 -> 580211 | K17: =J17-I17 -> 240298.5
C18: =Analyze!A14 -> Sprite | D18: =Analyze!B14 -> 366578 | E18: =Analyze!C14 -> 1353578.3 | F18: =E18-D18 -> 987000.3 | H18: =Analyze!A25 -> West Soda | I18: =Analyze!B25 -> 1170361.6 | J18: =Analyze!C25 -> 2070594.2 | K18: =J18-I18 -> 900232.6
C19: Total | D19: =SUM(D13:D18) -> 2423732.5 | E19: =SUM(E13:E18) -> 9592932.5 | F19: =SUM(F13:F18) -> 7169200 | H19: Total | I19: =SUM(I13:I18) -> 2423732.5 | J19: =SUM(J13:J18) -> 9592932.5 | K19: =SUM(K13:K18) -> 7169200
C21: Sales and Operating Profit Margin by Quarter

Sheet Resources
